LICENSE
README.md
pyrust/__init__.py
pyrust/_native.cp311-win_amd64.pyd
pyrust/analyzer/__init__.py
pyrust/analyzer/__main__.py
pyrust/analyzer/cli.py
pyrust/api.py
pyrust/cache/__init__.py
pyrust/profiler/__init__.py
pyrust/profiler/cli.py
pyrust/runtime/__init__.py
pyrust/transpiler/__init__.py
pyrust_native-0.0.2.dist-info/METADATA
pyrust_native-0.0.2.dist-info/WHEEL
pyrust_native-0.0.2.dist-info/entry_points.txt
pyrust_native-0.0.2.dist-info/licenses/LICENSE
pyrust_native-0.0.2.dist-info/RECORD
