Metadata-Version: 2.4
Name: pyrust-native
Version: 0.0.2
Classifier: Programming Language :: Python :: 3
Classifier: Programming Language :: Python :: 3.10
Classifier: Programming Language :: Python :: 3.11
Classifier: Programming Language :: Python :: 3.12
Classifier: Programming Language :: Rust
Classifier: License :: OSI Approved :: MIT License
Classifier: Operating System :: OS Independent
Requires-Dist: build>=1.2 ; extra == 'dev'
Requires-Dist: pytest>=8 ; extra == 'dev'
Requires-Dist: ruff>=0.5 ; extra == 'dev'
Requires-Dist: mypy>=1.10 ; extra == 'dev'
Requires-Dist: maturin>=1.6,<2.0 ; extra == 'dev'
Requires-Dist: ipython>=8 ; extra == 'dev'
Requires-Dist: maturin>=1.6,<2.0 ; extra == 'rust'
Requires-Dist: ipython>=8 ; extra == 'examples'
Requires-Dist: rich>=13 ; extra == 'examples'
Requires-Dist: mkdocs>=1.5 ; extra == 'docs'
Requires-Dist: mkdocs-material>=9.5 ; extra == 'docs'
Provides-Extra: dev
Provides-Extra: rust
Provides-Extra: examples
Provides-Extra: docs
License-File: LICENSE
Summary: Python-first auto-optimizer that rustifies hotspots (skeleton repo)
Keywords: rust,pyo3,maturin,cython,jit,optimizer
Author: PyRust Contributors
Maintainer: PyRust Maintainers
License: MIT
Requires-Python: >=3.10
Project-URL: Homepage, https://github.com/pyrust-dev/pyrust
Project-URL: Repository, https://github.com/pyrust-dev/pyrust
Project-URL: Issues, https://github.com/pyrust-dev/pyrust/issues
Project-URL: Documentation, https://pyrust-dev.github.io/pyrust/
Project-URL: Changelog, https://github.com/pyrust-dev/pyrust/blob/main/CHANGELOG.md
Project-URL: Discussions, https://github.com/pyrust-dev/pyrust/discussions
Project-URL: Release Notes, https://github.com/pyrust-dev/pyrust/releases
